neuspell/__init__.py
neuspell/commons.py
neuspell/corrector.py
neuspell/corrector_bertsclstm.py
neuspell/corrector_cnnlstm.py
neuspell/corrector_elmosclstm.py
neuspell/corrector_lstmlstm.py
neuspell/corrector_sclstm.py
neuspell/corrector_sclstmbert.py
neuspell/corrector_sclstmelmo.py
neuspell/corrector_subwordbert.py
neuspell/util.py
neuspell/noising/__init__.py
neuspell/noising/_util.py
neuspell/noising/crn_utils.py
neuspell/noising/downloads.py
neuspell/noising/noiser.py
neuspell/noising/pcrn_utils.py
neuspell/noising/wrn_utils.py
neuspell/off_the_shelf/__init__.py
neuspell/off_the_shelf/corrector_aspell.py
neuspell/off_the_shelf/corrector_jamspell.py
neuspell/off_the_shelf/util.py
neuspell/seq_modeling/__init__.py
neuspell/seq_modeling/bertsclstm.py
neuspell/seq_modeling/cnnlstm.py
neuspell/seq_modeling/downloads.py
neuspell/seq_modeling/elmosclstm.py
neuspell/seq_modeling/elmosctrans.py
neuspell/seq_modeling/evals.py
neuspell/seq_modeling/helpers.py
neuspell/seq_modeling/helpers2.py
neuspell/seq_modeling/lstmlstm.py
neuspell/seq_modeling/models.py
neuspell/seq_modeling/sclstm.py
neuspell/seq_modeling/sclstmbert.py
neuspell/seq_modeling/sclstmelmo.py
neuspell/seq_modeling/subwordbert.py
neuspell/seq_modeling/subwordelmo.py
neuspell/seq_modeling/util.py
neuspellmyntra-1.0.0.dist-info/LICENSE
neuspellmyntra-1.0.0.dist-info/METADATA
neuspellmyntra-1.0.0.dist-info/WHEEL
neuspellmyntra-1.0.0.dist-info/top_level.txt
neuspellmyntra-1.0.0.dist-info/RECORD
